Workbook

Sheet Parameters
C1: Reporting Period (or Fiscal Year)
C3: Select the Start month of the Fiscal Year from the drop-down list (yellow highlighted cell).
A5: January | C5: Fiscal Start Month | D5: April | E5: =IF(Parameters!$D$5="January",1,IF(Parameters!$D$5="February",2,IF(Parameters!$D$5="March",3,IF(Parameters!$D$5="April",4,IF(Parameters!$D$5="May",5,IF(Parameters!$D$5="June",6,IF(Parameters!$D$5="July",7,IF(Parameters!$D$5="August",8,IF(Parameters!$D$5="September",9,IF(Parameters!$D$5="October",10,IF(Parameters!$D$5="November",11,12))))))))))) -> 4
A6: February | C6: Fiscal End Month | D6: =IF($D$5="January","December",IF($D$5="February","January",IF($D$5="March","February",IF($D$5="April","March",IF($D$5="May","April",IF($D$5="June","May",IF($D$5="July","June",IF($D$5="August","July",IF($D$5="September","August",IF($D$5="October","September",IF($D$5="November","October","November"))))))))))) -> March
A7: March
A8: April | C8: Auto-computed End Month Number
A9: May
A10: June | C10: End Month Number | D10: =IF(E5=1,12,E5-1) -> 3
A11: July
A12: August | C12: Follow the demo shown in the video to update the below:
A13: September | C13: - Power Query view: dimDate Table >>> FiscalYearEndMonth
A14: November
A15: December

Sheet _days
A1: 45474 | B1: Date
B2: 43831
B3: 43831
B4: 43831
B5: 43831
B6: 43831
B7: 43831
B8: 43831
B9: 43831
B10: 43832
B11: 43832
B12: 43832
B13: 43832
... B15798: 45411

Sheet Orders
A1: Order | B1: Date | C1: Company ID | D1: Country ID | E1: Product ID | F1: Quantity | G1: Price | H1: Total Price | I1: Discount | J1: Sales | K1: Unit Cost | L1: Cost | M1: Profit | N1: Return
A2: A20000100 | B2: =DATE(YEAR(_days!$B2)+(YEAR(TODAY())-YEAR(_days!$A$1)),MONTH(_days!$B2),DAY(_days!$B2)) -> 44197 | C2: A100001 | D2: C01 | E2: P001 | F2: 22 | G2: 115 | H2: 2530 | I2: 10 | J2: 2277 | K2: 50 | L2: 1100 | M2: 1177 | N2: N
A3: A20000101 | B3: =DATE(YEAR(_days!$B3)+(YEAR(TODAY())-YEAR(_days!$A$1)),MONTH(_days!$B3),DAY(_days!$B3)) -> 44197 | C3: A100002 | D3: C02 | E3: P002 | F3: 45 | G3: 85 | H3: 3825 | I3: 6 | J3: 3596 | K3: 29 | L3: 1305 | M3: 2291 | N3: N
A4: A20000102 | B4: =DATE(YEAR(_days!$B4)+(YEAR(TODAY())-YEAR(_days!$A$1)),MONTH(_days!$B4),DAY(_days!$B4)) -> 44197 | C4: A100003 | D4: C03 | E4: P003 | F4: 41 | G4: 331 | H4: 13571 | I4: 17 | J4: 11264 | K4: 114 | L4: 4674 | M4: 6590 | N4: N
A5: A20000103 | B5: =DATE(YEAR(_days!$B5)+(YEAR(TODAY())-YEAR(_days!$A$1)),MONTH(_days!$B5),DAY(_days!$B5)) -> 44197 | C5: A100004 | D5: C04 | E5: P004 | F5: 6 | G5: 38 | H5: 228 | I5: 14 | J5: 197 | K5: 13 | L5: 78 | M5: 119 | N5: N
A6: A20000104 | B6: =DATE(YEAR(_days!$B6)+(YEAR(TODAY())-YEAR(_days!$A$1)),MONTH(_days!$B6),DAY(_days!$B6)) -> 44197 | C6: A100005 | D6: C05 | E6: P005 | F6: 20 | G6: 279 | H6: 5580 | I6: 25 | J6: 4185 | K6: 93 | L6: 1860 | M6: 2325 | N6: N
A7: A20000105 | B7: =DATE(YEAR(_days!$B7)+(YEAR(TODAY())-YEAR(_days!$A$1)),MONTH(_days!$B7),DAY(_days!$B7)) -> 44197 | C7: A100006 | D7: C06 | E7: P006 | F7: 7 | G7: 489 | H7: 3423 | I7: 28 | J7: 2465 | K7: 163 | L7: 1141 | M7: 1324 | N7: N
A8: A20000106 | B8: =DATE(YEAR(_days!$B8)+(YEAR(TODAY())-YEAR(_days!$A$1)),MONTH(_days!$B8),DAY(_days!$B8)) -> 44197 | C8: A100007 | D8: C07 | E8: P007 | F8: 28 | G8: 58 | H8: 1624 | I8: 19 | J8: 1316 | K8: 23 | L8: 644 | M8: 672 | N8: N
A9: A20000107 | B9: =DATE(YEAR(_days!$B9)+(YEAR(TODAY())-YEAR(_days!$A$1)),MONTH(_days!$B9),DAY(_days!$B9)) -> 44197 | C9: A100008 | D9: C08 | E9: P008 | F9: 25 | G9: 196 | H9: 4900 | I9: 30 | J9: 3430 | K9: 89 | L9: 2225 | M9: 1205 | N9: N
A10: A20000108 | B10: =DATE(YEAR(_days!$B10)+(YEAR(TODAY())-YEAR(_days!$A$1)),MONTH(_days!$B10),DAY(_days!$B10)) -> 44198 | C10: A100009 | D10: C09 | E10: P009 | F10: 36 | G10: 339 | H10: 12204 | I10: 13 | J10: 10618 | K10: 147 | L10: 5292 | M10: 5326 | N10: N
A11: A20000109 | B11: =DATE(YEAR(_days!$B11)+(YEAR(TODAY())-YEAR(_days!$A$1)),MONTH(_days!$B11),DAY(_days!$B11)) -> 44198 | C11: A100010 | D11: C10 | E11: P010 | F11: 25 | G11: 90 | H11: 2250 | I11: 11 | J11: 2003 | K11: 45 | L11: 1125 | M11: 878 | N11: N
A12: A20000110 | B12: =DATE(YEAR(_days!$B12)+(YEAR(TODAY())-YEAR(_days!$A$1)),MONTH(_days!$B12),DAY(_days!$B12)) -> 44198 | C12: A100011 | D12: C04 | E12: P011 | F12: 29 | G12: 90 | H12: 2610 | I12: 0 | J12: 2610 | K12: 39 | L12: 1131 | M12: 1479 | N12: N
A13: A20000111 | B13: =DATE(YEAR(_days!$B13)+(YEAR(TODAY())-YEAR(_days!$A$1)),MONTH(_days!$B13),DAY(_days!$B13)) -> 44198 | C13: A100012 | D13: C09 | E13: P012 | F13: 7 | G13: 37 | H13: 259 | I13: 10 | J13: 234 | K13: 13 | L13: 91 | M13: 143 | N13: N
... A15798: A24001217 | B15798: =DATE(YEAR(_days!$B15798)+(YEAR(TODAY())-YEAR(_days!$A$1)),MONTH(_days!$B15798),DAY(_days!$B15798)) -> 45776 | C15798: A100007 | D15798: C08 | E15798: P029 | F15798: 6 | G15798: 269 | H15798: 1614 | I15798: 28 | J15798: 1163 | K15798: 122 | L15798: 732 | M15798: 431 | N15798: N

Sheet Company
A1: Company ID | B1: Company Name | C1: Contact Person | D1: Address
A2: A100001 | B2: Fer Mal Group | C2: Israel Kerins
A3: A100002 | B3: Denturas Solutions | C3: Trev Tesimon
A4: A100003 | B4: OTY Lab | C4: Sanders Newnham
A5: A100004 | B5: Boriton Korea Holdings | C5: Arline Kelinge
A6: A100005 | B6: Hornma Holdings | C6: Pepita Coolbear
A7: A100006 | B7: YTL Inc. | C7: Pavlov Forri
A8: A100007 | B8: Danthod Company | C8: Hillary Pemberton
A9: A100008 | B9: Fil Dil Corp | C9: Alikee McQueen
A10: A100009 | B10: The Kenlum Co | C10: Justin Ewence
A11: A100010 | B11: Fullistical | C11: Marleah Abell
A12: A100011 | B12: Himito Group | C12: Liuka McKinnell
A13: A100012 | B13: WWL Inc. | C13: Prudi Schops
... A51: A100050 | B51: Contip, Inc. | C51: Wallace Stronghill

Sheet City
A1: City Code | B1: City Name
A2: C01 | B2: New York
A3: C02 | B3: Seattle
A4: C03 | B4: Chicago
A5: C04 | B5: Houston
A6: C05 | B6: Phoenix
A7: C06 | B7: Atlanta
A8: C07 | B8: Salt Lake City
A9: C08 | B9: San Diego
A10: C09 | B10: Jacksonville
A11: C10 | B11: San Jose

Sheet Category
A1: Cat ID | B1: Category Name
A2: Cat01 | B2: Electronics
A3: Cat02 | B3: Fashion
A4: Cat03 | B4: Furniture
A5: Cat04 | B5: Tools
A6: Cat05 | B6: Sporting

Sheet Product
A1: Product ID | B1: Product Name | C1: Description | D1: Cat ID | E1: Department | F1: Cost | G1: Price
A2: P001 | B2: Camera | C2: Description 1 | D2: Cat01 | E2: Dept_1 | F2: 50 | G2: 115
A3: P002 | B3: Shoe | C3: Description 2 | D3: Cat02 | E3: Dept_2 | F3: 29 | G3: 85
A4: P003 | B4: Side Table | C4: Description 3 | D4: Cat03 | E4: Dept_1 | F4: 114 | G4: 331
A5: P004 | B5: Milling Accessories | C5: Description 4 | D5: Cat04 | E5: Dept_3 | F5: 13 | G5: 38
A6: P005 | B6: Spin Bike | C6: Description 5 | D6: Cat05 | E6: Dept_2 | F6: 93 | G6: 279
A7: P006 | B7: Jewellery | C7: Description 6 | D7: Cat02 | E7: Dept_1 | F7: 163 | G7: 489
A8: P007 | B8: Fitness Plus | C8: Description 7 | D8: Cat05 | E8: Dept_4 | F8: 23 | G8: 58
A9: P008 | B9: Electronic Saw | C9: Description 8 | D9: Cat04 | E9: Dept_4 | F9: 89 | G9: 196
A10: P009 | B10: Dining Table | C10: Description 9 | D10: Cat03 | E10: Dept_2 | F10: 147 | G10: 339
A11: P010 | B11: Speakers | C11: Description 10 | D11: Cat01 | E11: Dept_5 | F11: 45 | G11: 90
A12: P011 | B12: Boxing Trust | C12: Description 11 | D12: Cat05 | E12: Dept_3 | F12: 39 | G12: 90
A13: P012 | B13: Abrasive Wheels | C13: Description 12 | D13: Cat04 | E13: Dept_6 | F13: 13 | G13: 37
... A51: P050 | B51: Power Drill | C51: Description 50 | D51: Cat04 | E51: Dept_2 | F51: 62 | G51: 143

Sheet Selection
A1: Line | B1: Selection
A2: 1 | B2: Sales
A3: 2 | B3: Orders
A4: 3 | B4: Returns
